{"id":128511,"primaryUUID":"4c0184f1-b106-41f3-ba84-594b6e5c5a60","secondaryUUID":"629af4d2-7ac1-4572-8bf4-35d8e89153e9","displayname":"Trident_of_the_Depths","basename":"TRIDENT","abilityid":0,"strength":14,"stamina":14,"agility":14,"dexterity":0,"procRate":0,"placeable":true,"intelligence":0,"wisdom":0,"charisma":0,"allowedClassNames":[],"allowedRaceNames":[],"questitem":false,"damage":14,"weaponabilityid":619,"attackspeed":130,"enchantment1val":0,"enchantment2val":0,"enchantment3val":0,"enchantment4val":0,"hpregen":3,"mpregen":3,"worth":1,"coreitem":false,"fireResist":0,"coldResist":0,"magicResist":0,"poisonResist":0,"diseaseResist":0,"magic":false,"elementalDamageType":0,"elementalDamageAmount":0,"spellscroll":false,"color":0,"dye":0,"isTemporary":false,"isConsumable":false,"consumableRequireQuestFlag":"","consumableRequireNotQuestFlag":"","baneUndead":0,"isAugmentation":false,"augmentationFitsSlotType":"NONE","discoverer":"Polyphemes","minLevel":60,"ac":0,"hp":140,"mana":0,"isExperienceBonus":false,"skillModType":"Slashing","skillModValue":20,"reagent":false,"languagePrimer":"","focusEffectId":0,"weaponDelay":30,"leatherRgbDecimal":-1,"requiredWeaponSkillType":"","artifact":false,"artifactFound":false,"skillModType2":"None","skillModValue2":0,"skillModType3":"None","skillModValue3":0,"skillModType4":"None","skillModValue4":0,"identifyMessage":"An ancient trident found among the dark ocean depths; once held by some forgotten ruler of an undersea kingdom; laying in wait for ages until another worth of its power finally retrieves it.","bandage":false,"equipmentSlot":"None","bookAuthor":"","bookPages":[],"neverDrop":false,"lastUpdatedTime":"Jan 7, 2019 9:19:10 PM","itemType":"None","QuestId":0,"appearanceId":0,"baneDmgBody":0,"baneDmgRace":0,"baneDmgBodyAmount":0,"baneDmgRaceAmount":0}
