{"id":146562,"primaryUUID":"6c3404bb-88c2-4af8-9f32-684a81e897d7","secondaryUUID":"0ef6fead-9b84-47bd-b97e-deb4645a91be","displayname":"Unholy Sword of the Kotengu","basename":"IRON_SWORD","abilityid":0,"strength":5,"stamina":3,"agility":0,"dexterity":0,"procRate":0,"placeable":false,"intelligence":2,"wisdom":0,"charisma":0,"allowedClassNames":["SHADOWKNIGHT"],"allowedRaceNames":[],"questitem":false,"damage":18,"weaponabilityid":0,"attackspeed":0,"enchantment1val":0,"enchantment2val":0,"enchantment3val":0,"enchantment4val":0,"hpregen":0,"mpregen":0,"worth":15,"coreitem":false,"fireResist":0,"coldResist":0,"magicResist":0,"poisonResist":0,"diseaseResist":0,"magic":false,"elementalDamageType":0,"elementalDamageAmount":0,"spellscroll":false,"color":0,"dye":0,"isTemporary":false,"isConsumable":false,"consumableRequireQuestFlag":"","consumableRequireNotQuestFlag":"","baneUndead":0,"isAugmentation":false,"augmentationFitsSlotType":"NONE","discoverer":"","minLevel":1,"ac":0,"hp":3,"mana":10,"isExperienceBonus":false,"skillModType":"None","skillModValue":0,"reagent":false,"languagePrimer":"","focusEffectId":0,"weaponDelay":43,"leatherRgbDecimal":-1,"requiredWeaponSkillType":"","artifact":false,"artifactFound":false,"skillModType2":"None","skillModValue2":0,"skillModType3":"None","skillModValue3":0,"skillModType4":"None","skillModValue4":0,"identifyMessage":"","bandage":false,"equipmentSlot":"None","bookAuthor":"","bookPages":[],"neverDrop":false,"lastUpdatedTime":"Apr 20, 2020 5:17:44 PM","itemType":"TwoHandSlashing","QuestId":0,"appearanceId":7,"baneDmgBody":0,"baneDmgRace":0,"baneDmgBodyAmount":0,"baneDmgRaceAmount":0}