{"id":165920,"primaryUUID":"02c3edb5-24be-45aa-b8b7-9cda46ae3d7e","secondaryUUID":"dffd2103-9b36-46b0-a81a-41c95720154a","displayname":"Melodic Greaves Of the TreeTalkers","basename":"CHAINMAIL_LEGGINGS","abilityid":0,"strength":12,"stamina":0,"agility":13,"dexterity":14,"procRate":0,"placeable":false,"intelligence":0,"wisdom":0,"charisma":12,"allowedClassNames":["BARD"],"allowedRaceNames":[],"questitem":false,"damage":0,"weaponabilityid":0,"attackspeed":0,"enchantment1val":0,"enchantment2val":0,"enchantment3val":0,"enchantment4val":0,"hpregen":0,"mpregen":0,"worth":90,"coreitem":false,"fireResist":0,"coldResist":3,"magicResist":2,"poisonResist":2,"diseaseResist":0,"magic":false,"elementalDamageType":0,"elementalDamageAmount":0,"spellscroll":false,"color":0,"dye":0,"isTemporary":false,"isConsumable":false,"consumableRequireQuestFlag":"","consumableRequireNotQuestFlag":"","baneUndead":0,"isAugmentation":false,"augmentationFitsSlotType":"NONE","discoverer":"","minLevel":50,"ac":25,"hp":82,"mana":31,"isExperienceBonus":false,"skillModType":"None","skillModValue":0,"reagent":false,"languagePrimer":"","focusEffectId":0,"weaponDelay":30,"leatherRgbDecimal":-1,"requiredWeaponSkillType":"","artifact":false,"artifactFound":false,"skillModType2":"None","skillModValue2":0,"skillModType3":"None","skillModValue3":0,"skillModType4":"None","skillModValue4":0,"identifyMessage":"","bandage":false,"equipmentSlot":"None","bookAuthor":"","bookPages":[],"neverDrop":false,"lastUpdatedTime":"Apr 20, 2020 5:17:44 PM","itemType":"Clothing","QuestId":0,"appearanceId":10,"baneDmgBody":0,"baneDmgRace":0,"baneDmgBodyAmount":0,"baneDmgRaceAmount":0}