{"id":182181,"primaryUUID":"d1ffab20-c1c1-48f6-b299-c59f136f7e98","secondaryUUID":"119e4879-9173-4dc7-aae8-152fe40f6165","displayname":"Stoic Tunic of the Water Nymph","basename":"LEATHER_CHESTPLATE","abilityid":0,"strength":7,"stamina":0,"agility":7,"dexterity":6,"procRate":0,"placeable":false,"intelligence":0,"wisdom":0,"charisma":0,"allowedClassNames":["MONK"],"allowedRaceNames":[],"questitem":false,"damage":0,"weaponabilityid":0,"attackspeed":0,"enchantment1val":0,"enchantment2val":0,"enchantment3val":0,"enchantment4val":0,"hpregen":0,"mpregen":0,"worth":45,"coreitem":false,"fireResist":1,"coldResist":1,"magicResist":1,"poisonResist":1,"diseaseResist":0,"magic":false,"elementalDamageType":0,"elementalDamageAmount":0,"spellscroll":false,"color":0,"dye":0,"isTemporary":false,"isConsumable":false,"consumableRequireQuestFlag":"","consumableRequireNotQuestFlag":"","baneUndead":0,"isAugmentation":false,"augmentationFitsSlotType":"NONE","discoverer":"Ailin_Darkashe","minLevel":20,"ac":11,"hp":60,"mana":44,"isExperienceBonus":false,"skillModType":"None","skillModValue":0,"reagent":false,"languagePrimer":"","focusEffectId":0,"weaponDelay":30,"leatherRgbDecimal":-1,"requiredWeaponSkillType":"","artifact":false,"artifactFound":false,"skillModType2":"None","skillModValue2":0,"skillModType3":"None","skillModValue3":0,"skillModType4":"None","skillModValue4":0,"identifyMessage":"","bandage":false,"equipmentSlot":"None","bookAuthor":"","bookPages":[],"neverDrop":false,"lastUpdatedTime":"Apr 20, 2020 5:17:44 PM","itemType":"Clothing","QuestId":0,"appearanceId":12,"baneDmgBody":0,"baneDmgRace":0,"baneDmgBodyAmount":0,"baneDmgRaceAmount":0}