{"id":234143,"primaryUUID":"b46a26dd-8092-487d-90eb-c27f8c307e17","secondaryUUID":"8b9f5cb1-9df6-4bfe-9dfb-db15aa21b3e8","displayname":"Feral Warclub of the Arena","basename":"IRON_SHOVEL","abilityid":0,"strength":19,"stamina":15,"agility":18,"dexterity":16,"procRate":0,"placeable":false,"intelligence":0,"wisdom":16,"charisma":0,"allowedClassNames":["BEASTLORD"],"allowedRaceNames":[],"questitem":false,"damage":17,"weaponabilityid":0,"attackspeed":0,"enchantment1val":0,"enchantment2val":0,"enchantment3val":0,"enchantment4val":0,"hpregen":0,"mpregen":0,"worth":120,"coreitem":false,"fireResist":0,"coldResist":1,"magicResist":1,"poisonResist":0,"diseaseResist":4,"magic":false,"elementalDamageType":0,"elementalDamageAmount":0,"spellscroll":false,"color":0,"dye":0,"isTemporary":false,"isConsumable":false,"consumableRequireQuestFlag":"","consumableRequireNotQuestFlag":"","consumableRequireInZone":0,"baneUndead":0,"isAugmentation":false,"augmentationFitsSlotType":"NONE","discoverer":"","minLevel":70,"ac":0,"hp":50,"mana":100,"isExperienceBonus":false,"skillModType":"None","skillModValue":0,"reagent":false,"languagePrimer":"","focusEffectId":0,"weaponDelay":25,"leatherRgbDecimal":-1,"requiredWeaponSkillType":"","artifact":false,"artifactFound":false,"skillModType2":"None","skillModValue2":0,"skillModType3":"None","skillModValue3":0,"skillModType4":"None","skillModValue4":0,"identifyMessage":"","bandage":false,"equipmentSlot":"None","bookAuthor":"","bookPages":[],"neverDrop":false,"lastUpdatedTime":"May 9, 2020 11:58:28 PM","itemType":"OneHandBlunt","QuestId":0,"appearanceId":15,"baneDmgBody":0,"baneDmgRace":0,"baneDmgBodyAmount":0,"baneDmgRaceAmount":0}